webviz_subsurface/__init__.py
webviz_subsurface/_version.py
webviz_subsurface/smry2arrow_batch.py
webviz_subsurface/_abbreviations/__init__.py
webviz_subsurface/_abbreviations/number_formatting.py
webviz_subsurface/_abbreviations/reservoir_simulation.py
webviz_subsurface/_abbreviations/volume_terminology.py
webviz_subsurface/_abbreviations/abbreviation_data/reservoir_simulation_unit_terminology.json
webviz_subsurface/_abbreviations/abbreviation_data/si_prefixes.json
webviz_subsurface/_abbreviations/abbreviation_data/volume_terminology.json
webviz_subsurface/_assets/css/block_options.css
webviz_subsurface/_assets/css/container.css
webviz_subsurface/_assets/css/inplace_volumes.css
webviz_subsurface/_assets/css/modal.css
webviz_subsurface/_assets/css/structural_uncertainty.css
webviz_subsurface/_assets/js/clientside_functions.js
webviz_subsurface/_components/__init__.py
webviz_subsurface/_components/color_picker.py
webviz_subsurface/_components/parameter_filter.py
webviz_subsurface/_components/tornado/__init__.py
webviz_subsurface/_components/tornado/_tornado_bar_chart.py
webviz_subsurface/_components/tornado/_tornado_data.py
webviz_subsurface/_components/tornado/_tornado_table.py
webviz_subsurface/_components/tornado/tornado_widget.py
webviz_subsurface/_datainput/__init__.py
webviz_subsurface/_datainput/eclipse_unit.py
webviz_subsurface/_datainput/fmu_input.py
webviz_subsurface/_datainput/from_timeseries_cumulatives.py
webviz_subsurface/_datainput/grid.py
webviz_subsurface/_datainput/history_match.py
webviz_subsurface/_datainput/image_processing.py
webviz_subsurface/_datainput/inplace_volumes.py
webviz_subsurface/_datainput/pvt_data.py
webviz_subsurface/_datainput/relative_permeability.py
webviz_subsurface/_datainput/seismic.py
webviz_subsurface/_datainput/surface.py
webviz_subsurface/_datainput/units.py
webviz_subsurface/_datainput/well.py
webviz_subsurface/_datainput/well_completions.py
webviz_subsurface/_datainput/xsection.py
webviz_subsurface-0.2.44.dist-info/licenses/LICENSE
webviz_subsurface-0.2.44.dist-info/licenses/LICENSE.chromedriver
webviz_subsurface-0.2.44.dist-info/METADATA
webviz_subsurface-0.2.44.dist-info/WHEEL
webviz_subsurface-0.2.44.dist-info/entry_points.txt
webviz_subsurface-0.2.44.dist-info/top_level.txt
webviz_subsurface-0.2.44.dist-info/RECORD
