Metadata-Version: 2.4
Name: webviz-subsurface
Version: 0.2.44
Summary: Webviz config plugins for subsurface data
Author: R&T Equinor
License:                     GNU GENERAL PUBLIC LICENSE
Project-URL: Homepage, https://github.com/equinor/webviz-subsurface
Project-URL: Documentation, https://equinor.github.io/webviz-subsurface
Project-URL: Source, https://github.com/equinor/webviz-subsurface
Project-URL: Tracker, https://github.com/equinor/webviz-subsurface/issues
Classifier: Programming Language :: Python :: 3
Classifier: Operating System :: OS Independent
Classifier: Natural Language :: English
Classifier: Environment :: Web Environment
Classifier: Framework :: Dash
Classifier: Framework :: Flask
Classifier: Topic :: Multimedia :: Graphics
Classifier: Topic :: Scientific/Engineering
Classifier: Topic :: Scientific/Engineering :: Visualization
Classifier: License :: OSI Approved :: GNU General Public License v3 (GPLv3)
Requires-Python: ~=3.11
License-File: LICENSE
License-File: LICENSE.chromedriver
Requires-Dist: dash<3,>=2.0.0
Requires-Dist: dash_bootstrap_components>=0.10.3
Requires-Dist: dash-daq>=0.5.0
Requires-Dist: defusedxml>=0.6.0
Requires-Dist: res2df>=1.0; sys_platform == "linux"
Requires-Dist: flask-caching
Requires-Dist: fmu-ensemble>=1.2.3
Requires-Dist: fmu-tools>=1.8
Requires-Dist: geojson>=2.5.0
Requires-Dist: jsonschema>=3.2.0
Requires-Dist: opm>=2023.10; sys_platform == "linux"
Requires-Dist: pandas<3,>=1.1.5
Requires-Dist: pillow>=6.1
Requires-Dist: pyarrow>=5.0.0
Requires-Dist: pyjwt>=2.6.0
Requires-Dist: pyscal>=0.7.5
Requires-Dist: scipy>=1.16
Requires-Dist: statsmodels>=0.14.5
Requires-Dist: xtgeo>=2.20.0
Requires-Dist: vtk>=9.2.2
Requires-Dist: webviz-config>=0.6.5
Requires-Dist: webviz-subsurface-components>=1.0.3
Provides-Extra: tests
Requires-Dist: bandit; extra == "tests"
Requires-Dist: black<24,>=22.1; extra == "tests"
Requires-Dist: dash[testing]; extra == "tests"
Requires-Dist: isort; extra == "tests"
Requires-Dist: mypy<1.12; extra == "tests"
Requires-Dist: pylint<3.2.0; extra == "tests"
Requires-Dist: pytest-mock; extra == "tests"
Requires-Dist: pytest-xdist; extra == "tests"
Requires-Dist: pytest-forked; extra == "tests"
Requires-Dist: selenium>=3.141; extra == "tests"
Requires-Dist: types-setuptools; extra == "tests"
Requires-Dist: types-pyyaml; extra == "tests"
Dynamic: license-file
